baidufanyiformind/__init__.py
baidufanyiformind-0.0.2.dist-info/METADATA
baidufanyiformind-0.0.2.dist-info/WHEEL
baidufanyiformind-0.0.2.dist-info/top_level.txt
baidufanyiformind-0.0.2.dist-info/RECORD
