Metadata-Version: 2.1
Name: baidufanyiformind
Version: 0.0.2
Summary: A package for baidufanyi
Home-page: https://gitee.com/liliang9693/baidufanyiformind
Author: liliang
Author-email: liang.li@dfrobot.com
Classifier: Programming Language :: Python :: 3
Classifier: License :: OSI Approved :: MIT License
Classifier: Operating System :: OS Independent
Requires-Python: >=3.4
